<resources>
    <style name="AppTheme" parent="Theme.AppCompat.Light.NoActionBar">
		<item name="windowNoTitle">true</item>
		<item name="windowActionBar">false</item>
        <item name="colorPrimary">@color/colorPrimary</item>
        <item name="colorPrimaryDark">@color/colorPrimaryDark</item>
        <item name="colorAccent">@color/colorAccent</item>
    </style>
	<style name="MyDrawerArrowStyle" parent="Widget.AppCompat.DrawerArrowToggle">
		<item name="color">#F5F5F5</item>
		<item name="spinBars">true</item>
	</style>
</resources>
